[
  {
    "id": "PED-20260601215509-293",
    "createdAt": "2026-06-02T00:55:09.757Z",
    "updatedAt": "2026-06-02T00:55:10.597Z",
    "status": "Pendente",
    "archived": false,
    "isDuplicate": false,
    "preposto": {
      "codigo": "109839",
      "nome": "MARIANA"
    },
    "clienteCodigo": "9173",
    "clienteNome": "CARLOS ANTONIO BRITO",
    "prazo": "Z35 - 63/91/119 D",
    "campanha": "",
    "observacoes": "",
    "totals": {
      "packs": 1,
      "units": 12
    },
    "items": [
      {
        "codigo": "43447473",
        "produto": "CORRE VENTO 3",
        "cor": "ARTPTO",
        "num": "2",
        "gci": "7488389",
        "ebm": "13313615",
        "amount": 1,
        "mode": "boxed",
        "packSize": 12,
        "totalUnits": 12,
        "grade": [
          {
            "size": "37",
            "qty": 1
          },
          {
            "size": "38",
            "qty": 2
          },
          {
            "size": "39",
            "qty": 2
          },
          {
            "size": "40",
            "qty": 3
          },
          {
            "size": "41",
            "qty": 2
          },
          {
            "size": "42",
            "qty": 1
          },
          {
            "size": "43",
            "qty": 1
          }
        ],
        "prevFaturamento": "16/06/2026"
      }
    ]
  },
  {
    "id": "PED-20260601215652-356",
    "createdAt": "2026-06-02T00:56:52.020Z",
    "updatedAt": "2026-06-02T00:56:52.861Z",
    "status": "Pendente",
    "archived": false,
    "isDuplicate": false,
    "preposto": {
      "codigo": "109839",
      "nome": "MARIANA"
    },
    "clienteCodigo": "4098088",
    "clienteNome": "SALATIEL HENRIQUE VALÉRIO",
    "prazo": "Z35 - 63/91/119 D",
    "campanha": "",
    "observacoes": "",
    "totals": {
      "packs": 2,
      "units": 24
    },
    "items": [
      {
        "codigo": "43447473",
        "produto": "CORRE VENTO 3",
        "cor": "ARTPTO",
        "num": "2",
        "gci": "7488389",
        "ebm": "13313615",
        "amount": 1,
        "mode": "boxed",
        "packSize": 12,
        "totalUnits": 12,
        "grade": [
          {
            "size": "37",
            "qty": 1
          },
          {
            "size": "38",
            "qty": 2
          },
          {
            "size": "39",
            "qty": 2
          },
          {
            "size": "40",
            "qty": 3
          },
          {
            "size": "41",
            "qty": 2
          },
          {
            "size": "42",
            "qty": 1
          },
          {
            "size": "43",
            "qty": 1
          }
        ],
        "prevFaturamento": "16/06/2026"
      },
      {
        "codigo": "43447473",
        "produto": "CORRE VENTO 3",
        "cor": "PTO/CH",
        "num": "10",
        "gci": "6901048",
        "ebm": "12715275",
        "amount": 1,
        "mode": "boxed",
        "packSize": 12,
        "totalUnits": 12,
        "grade": [
          {
            "size": "38",
            "qty": 1
          },
          {
            "size": "39",
            "qty": 2
          },
          {
            "size": "40",
            "qty": 3
          },
          {
            "size": "41",
            "qty": 2
          },
          {
            "size": "42",
            "qty": 2
          },
          {
            "size": "43",
            "qty": 1
          },
          {
            "size": "44",
            "qty": 1
          }
        ],
        "prevFaturamento": "30/06/2026"
      }
    ]
  },
  {
    "id": "PED-20260601215801-684",
    "createdAt": "2026-06-02T00:58:01.231Z",
    "updatedAt": "2026-06-02T00:58:02.078Z",
    "status": "Pendente",
    "archived": false,
    "isDuplicate": false,
    "preposto": {
      "codigo": "109839",
      "nome": "MARIANA"
    },
    "clienteCodigo": "1810796",
    "clienteNome": "A K VILA",
    "prazo": "Z35 - 63/91/119 D",
    "campanha": "",
    "observacoes": "",
    "totals": {
      "packs": 1,
      "units": 12
    },
    "items": [
      {
        "codigo": "43447473",
        "produto": "CORRE VENTO 3",
        "cor": "ARTPTO",
        "num": "2",
        "gci": "7488389",
        "ebm": "13313615",
        "amount": 1,
        "mode": "boxed",
        "packSize": 12,
        "totalUnits": 12,
        "grade": [
          {
            "size": "37",
            "qty": 1
          },
          {
            "size": "38",
            "qty": 2
          },
          {
            "size": "39",
            "qty": 2
          },
          {
            "size": "40",
            "qty": 3
          },
          {
            "size": "41",
            "qty": 2
          },
          {
            "size": "42",
            "qty": 1
          },
          {
            "size": "43",
            "qty": 1
          }
        ],
        "prevFaturamento": "16/06/2026"
      }
    ]
  },
  {
    "id": "PED-20260601215853-853",
    "createdAt": "2026-06-02T00:58:53.319Z",
    "updatedAt": "2026-06-02T00:58:54.173Z",
    "status": "Pendente",
    "archived": false,
    "isDuplicate": false,
    "preposto": {
      "codigo": "109839",
      "nome": "MARIANA"
    },
    "clienteCodigo": "1633552",
    "clienteNome": "FABRICIA LIMA",
    "prazo": "Z35 - 63/91/119 D",
    "campanha": "",
    "observacoes": "",
    "totals": {
      "packs": 1,
      "units": 12
    },
    "items": [
      {
        "codigo": "43447473",
        "produto": "CORRE VENTO 3",
        "cor": "ARTPTO",
        "num": "2",
        "gci": "7488389",
        "ebm": "13313615",
        "amount": 1,
        "mode": "boxed",
        "packSize": 12,
        "totalUnits": 12,
        "grade": [
          {
            "size": "37",
            "qty": 1
          },
          {
            "size": "38",
            "qty": 2
          },
          {
            "size": "39",
            "qty": 2
          },
          {
            "size": "40",
            "qty": 3
          },
          {
            "size": "41",
            "qty": 2
          },
          {
            "size": "42",
            "qty": 1
          },
          {
            "size": "43",
            "qty": 1
          }
        ],
        "prevFaturamento": "16/06/2026"
      }
    ]
  },
  {
    "id": "PED-20260601215953-292",
    "createdAt": "2026-06-02T00:59:53.971Z",
    "updatedAt": "2026-06-02T00:59:54.810Z",
    "status": "Pendente",
    "archived": false,
    "isDuplicate": false,
    "preposto": {
      "codigo": "109839",
      "nome": "MARIANA"
    },
    "clienteCodigo": "66817",
    "clienteNome": "KELLY ARAUJO",
    "prazo": "Z35 - 63/91/119 D",
    "campanha": "",
    "observacoes": "",
    "totals": {
      "packs": 2,
      "units": 24
    },
    "items": [
      {
        "codigo": "43447473",
        "produto": "CORRE VENTO 3",
        "cor": "ARTPTO",
        "num": "2",
        "gci": "7488389",
        "ebm": "13313615",
        "amount": 1,
        "mode": "boxed",
        "packSize": 12,
        "totalUnits": 12,
        "grade": [
          {
            "size": "37",
            "qty": 1
          },
          {
            "size": "38",
            "qty": 2
          },
          {
            "size": "39",
            "qty": 2
          },
          {
            "size": "40",
            "qty": 3
          },
          {
            "size": "41",
            "qty": 2
          },
          {
            "size": "42",
            "qty": 1
          },
          {
            "size": "43",
            "qty": 1
          }
        ],
        "prevFaturamento": "16/06/2026"
      },
      {
        "codigo": "43447473",
        "produto": "CORRE VENTO 3",
        "cor": "PTO/CH",
        "num": "10",
        "gci": "6901048",
        "ebm": "12715275",
        "amount": 1,
        "mode": "boxed",
        "packSize": 12,
        "totalUnits": 12,
        "grade": [
          {
            "size": "38",
            "qty": 1
          },
          {
            "size": "39",
            "qty": 2
          },
          {
            "size": "40",
            "qty": 3
          },
          {
            "size": "41",
            "qty": 2
          },
          {
            "size": "42",
            "qty": 2
          },
          {
            "size": "43",
            "qty": 1
          },
          {
            "size": "44",
            "qty": 1
          }
        ],
        "prevFaturamento": "30/06/2026"
      }
    ]
  },
  {
    "id": "PED-20260601220046-383",
    "createdAt": "2026-06-02T01:00:46.594Z",
    "updatedAt": "2026-06-02T01:00:47.446Z",
    "status": "Pendente",
    "archived": false,
    "isDuplicate": false,
    "preposto": {
      "codigo": "109839",
      "nome": "MARIANA"
    },
    "clienteCodigo": "71995",
    "clienteNome": "ANTONIO LOURIVAL",
    "prazo": "Z35 - 63/91/119 D",
    "campanha": "",
    "observacoes": "",
    "totals": {
      "packs": 2,
      "units": 24
    },
    "items": [
      {
        "codigo": "43447473",
        "produto": "CORRE VENTO 3",
        "cor": "ARTPTO",
        "num": "2",
        "gci": "7488389",
        "ebm": "13313615",
        "amount": 1,
        "mode": "boxed",
        "packSize": 12,
        "totalUnits": 12,
        "grade": [
          {
            "size": "37",
            "qty": 1
          },
          {
            "size": "38",
            "qty": 2
          },
          {
            "size": "39",
            "qty": 2
          },
          {
            "size": "40",
            "qty": 3
          },
          {
            "size": "41",
            "qty": 2
          },
          {
            "size": "42",
            "qty": 1
          },
          {
            "size": "43",
            "qty": 1
          }
        ],
        "prevFaturamento": "16/06/2026"
      },
      {
        "codigo": "43447473",
        "produto": "CORRE VENTO 3",
        "cor": "PTO/CH",
        "num": "10",
        "gci": "6901048",
        "ebm": "12715275",
        "amount": 1,
        "mode": "boxed",
        "packSize": 12,
        "totalUnits": 12,
        "grade": [
          {
            "size": "38",
            "qty": 1
          },
          {
            "size": "39",
            "qty": 2
          },
          {
            "size": "40",
            "qty": 3
          },
          {
            "size": "41",
            "qty": 2
          },
          {
            "size": "42",
            "qty": 2
          },
          {
            "size": "43",
            "qty": 1
          },
          {
            "size": "44",
            "qty": 1
          }
        ],
        "prevFaturamento": "30/06/2026"
      }
    ]
  },
  {
    "id": "PED-20260601220147-892",
    "createdAt": "2026-06-02T01:01:47.659Z",
    "updatedAt": "2026-06-02T01:01:48.517Z",
    "status": "Pendente",
    "archived": false,
    "isDuplicate": false,
    "preposto": {
      "codigo": "109839",
      "nome": "MARIANA"
    },
    "clienteCodigo": "71357",
    "clienteNome": "JOSE IRLANDO",
    "prazo": "Z35 - 63/91/119 D",
    "campanha": "",
    "observacoes": "",
    "totals": {
      "packs": 2,
      "units": 24
    },
    "items": [
      {
        "codigo": "43447473",
        "produto": "CORRE VENTO 3",
        "cor": "ARTPTO",
        "num": "2",
        "gci": "7488389",
        "ebm": "13313615",
        "amount": 1,
        "mode": "boxed",
        "packSize": 12,
        "totalUnits": 12,
        "grade": [
          {
            "size": "37",
            "qty": 1
          },
          {
            "size": "38",
            "qty": 2
          },
          {
            "size": "39",
            "qty": 2
          },
          {
            "size": "40",
            "qty": 3
          },
          {
            "size": "41",
            "qty": 2
          },
          {
            "size": "42",
            "qty": 1
          },
          {
            "size": "43",
            "qty": 1
          }
        ],
        "prevFaturamento": "16/06/2026"
      },
      {
        "codigo": "43447473",
        "produto": "CORRE VENTO 3",
        "cor": "PTO/CH",
        "num": "10",
        "gci": "6901048",
        "ebm": "12715275",
        "amount": 1,
        "mode": "boxed",
        "packSize": 12,
        "totalUnits": 12,
        "grade": [
          {
            "size": "38",
            "qty": 1
          },
          {
            "size": "39",
            "qty": 2
          },
          {
            "size": "40",
            "qty": 3
          },
          {
            "size": "41",
            "qty": 2
          },
          {
            "size": "42",
            "qty": 2
          },
          {
            "size": "43",
            "qty": 1
          },
          {
            "size": "44",
            "qty": 1
          }
        ],
        "prevFaturamento": "30/06/2026"
      }
    ]
  },
  {
    "id": "PED-20260601220249-825",
    "createdAt": "2026-06-02T01:02:49.476Z",
    "updatedAt": "2026-06-02T01:02:50.344Z",
    "status": "Pendente",
    "archived": false,
    "isDuplicate": false,
    "preposto": {
      "codigo": "109839",
      "nome": "MARIANA"
    },
    "clienteCodigo": "97922",
    "clienteNome": "MARIA APARECIDA",
    "prazo": "Z35 - 63/91/119 D",
    "campanha": "",
    "observacoes": "",
    "totals": {
      "packs": 2,
      "units": 24
    },
    "items": [
      {
        "codigo": "43447473",
        "produto": "CORRE VENTO 3",
        "cor": "ARTPTO",
        "num": "3",
        "gci": "7488389",
        "ebm": "13313615",
        "amount": 1,
        "mode": "boxed",
        "packSize": 12,
        "totalUnits": 12,
        "grade": [
          {
            "size": "38",
            "qty": 1
          },
          {
            "size": "39",
            "qty": 2
          },
          {
            "size": "40",
            "qty": 3
          },
          {
            "size": "41",
            "qty": 2
          },
          {
            "size": "42",
            "qty": 2
          },
          {
            "size": "43",
            "qty": 1
          },
          {
            "size": "44",
            "qty": 1
          }
        ],
        "prevFaturamento": "16/06/2026"
      },
      {
        "codigo": "43447473",
        "produto": "CORRE VENTO 3",
        "cor": "PTO/CH",
        "num": "10",
        "gci": "6901048",
        "ebm": "12715275",
        "amount": 1,
        "mode": "boxed",
        "packSize": 12,
        "totalUnits": 12,
        "grade": [
          {
            "size": "38",
            "qty": 1
          },
          {
            "size": "39",
            "qty": 2
          },
          {
            "size": "40",
            "qty": 3
          },
          {
            "size": "41",
            "qty": 2
          },
          {
            "size": "42",
            "qty": 2
          },
          {
            "size": "43",
            "qty": 1
          },
          {
            "size": "44",
            "qty": 1
          }
        ],
        "prevFaturamento": "30/06/2026"
      }
    ]
  },
  {
    "id": "PED-20260601220435-472",
    "createdAt": "2026-06-02T01:04:35.604Z",
    "updatedAt": "2026-06-02T01:04:36.589Z",
    "status": "Pendente",
    "archived": false,
    "isDuplicate": true,
    "preposto": {
      "codigo": "109839",
      "nome": "MARIANA"
    },
    "clienteCodigo": "9173",
    "clienteNome": "CARLOS ANTONIO BRITO",
    "prazo": "Z35 - 63/91/119 D",
    "campanha": "",
    "observacoes": "",
    "totals": {
      "packs": 3,
      "units": 36
    },
    "items": [
      {
        "codigo": "43447473",
        "produto": "CORRE VENTO 3",
        "cor": "ARTPTO",
        "num": "3",
        "gci": "7488389",
        "ebm": "13313615",
        "amount": 1,
        "mode": "boxed",
        "packSize": 12,
        "totalUnits": 12,
        "grade": [
          {
            "size": "38",
            "qty": 1
          },
          {
            "size": "39",
            "qty": 2
          },
          {
            "size": "40",
            "qty": 3
          },
          {
            "size": "41",
            "qty": 2
          },
          {
            "size": "42",
            "qty": 2
          },
          {
            "size": "43",
            "qty": 1
          },
          {
            "size": "44",
            "qty": 1
          }
        ],
        "prevFaturamento": "16/06/2026"
      },
      {
        "codigo": "43447473",
        "produto": "CORRE VENTO 3",
        "cor": "ALGMLT",
        "num": "6",
        "gci": "6901048",
        "ebm": "12715275",
        "amount": 1,
        "mode": "boxed",
        "packSize": 12,
        "totalUnits": 12,
        "grade": [
          {
            "size": "36",
            "qty": 1
          },
          {
            "size": "37",
            "qty": 2
          },
          {
            "size": "38",
            "qty": 3
          },
          {
            "size": "39",
            "qty": 3
          },
          {
            "size": "40",
            "qty": 2
          },
          {
            "size": "41",
            "qty": 1
          }
        ],
        "prevFaturamento": "30/06/2026"
      },
      {
        "codigo": "43447473",
        "produto": "CORRE VENTO 3",
        "cor": "PTO/CH",
        "num": "10",
        "gci": "6901048",
        "ebm": "12715275",
        "amount": 1,
        "mode": "boxed",
        "packSize": 12,
        "totalUnits": 12,
        "grade": [
          {
            "size": "38",
            "qty": 1
          },
          {
            "size": "39",
            "qty": 2
          },
          {
            "size": "40",
            "qty": 3
          },
          {
            "size": "41",
            "qty": 2
          },
          {
            "size": "42",
            "qty": 2
          },
          {
            "size": "43",
            "qty": 1
          },
          {
            "size": "44",
            "qty": 1
          }
        ],
        "prevFaturamento": "30/06/2026"
      }
    ]
  }
]